awa2/__init__.py
awa2/__main__.py
Awa2-1.1.1.dist-info/METADATA
Awa2-1.1.1.dist-info/WHEEL
Awa2-1.1.1.dist-info/top_level.txt
Awa2-1.1.1.dist-info/RECORD
