Metadata-Version: 2.1
Name: Awa2
Version: 1.1.1
Summary: Simple Setup
Author: XiangQinxi
Classifier: Programming Language :: Python :: 3
Classifier: License :: OSI Approved :: MIT License
Classifier: Operating System :: OS Independent
Requires-Python: >=3
Requires-Dist: rich
Requires-Dist: pick
Requires-Dist: toml
Requires-Dist: build
Requires-Dist: setuptools
Requires-Dist: twine
